setup.py
bdnd_probability/Binomialdistribution.py
bdnd_probability/Gaussiandistribution.py
bdnd_probability/Generaldistribution.py
bdnd_probability/__init__.py
bdnd_probability.egg-info/PKG-INFO
bdnd_probability.egg-info/SOURCES.txt
bdnd_probability.egg-info/dependency_links.txt
bdnd_probability.egg-info/not-zip-safe
bdnd_probability.egg-info/top_level.txt