Metadata-Version: 2.1
Name: bdnd-probability
Version: 0.1
Summary: Gaussian and binomial distributions
Home-page: UNKNOWN
Author: Adeniran Adedolapo
Author-email: adedolpson@gmail.com
License: UNKNOWN
Platform: UNKNOWN
